ratio_genetic_py-0.4.0.dist-info/METADATA
ratio_genetic_py-0.4.0.dist-info/WHEEL
ratio_genetic_py/__init__.py
ratio_genetic_py/py.typed
ratio_genetic_py/__init__.pyi
ratio_genetic_py/ratio_genetic_py.abi3.so
ratio_genetic_py-0.4.0.dist-info/RECORD
