Metadata-Version: 2.4
Name: ratio-genetic-py
Version: 0.4.0
Classifier: Programming Language :: Rust
Classifier: Programming Language :: Python :: Implementation :: CPython
Classifier: Programming Language :: Python :: Implementation :: PyPy
Classifier: License :: OSI Approved :: GNU General Public License v3 or later (GPLv3+)
Classifier: Topic :: Scientific/Engineering :: Mathematics
Classifier: Topic :: Software Development :: Libraries
Classifier: Development Status :: 3 - Alpha
Requires-Dist: loguru >=0.7.3, <1.0.0
Summary: Python bindings for the ratio-genetic Rust crate.
Keywords: genetic,algorithms,rust,mathematics,sga,clustering,sequencing
Author-email: "Ratio Innovations B.V." <info@ratio-case.nl>
Requires-Python: >=3.7
